{"nodes":{"node:100000":{"location":{"x":20,"y":6505}},"node:100001":{"location":{"x":480,"y":5721}},"node:100002":{"location":{"x":940,"y":5721}},"node:100003":{"location":{"x":1400,"y":5721}},"node:100004":{"location":{"x":1860,"y":5721}},"node:100005":{"location":{"x":2320,"y":5413}},"node:100006":{"location":{"x":2780,"y":4596}},"node:100007":{"location":{"x":3240,"y":3855}},"node:100008":{"location":{"x":3700,"y":1592}},"node:100009":{"location":{"x":4160,"y":30}},"node:100010":{"location":{"x":4160,"y":155}},"node:100011":{"location":{"x":4160,"y":280}},"node:100012":{"location":{"x":4620,"y":280}},"node:100013":{"location":{"x":4160,"y":405}},"node:100014":{"location":{"x":4620,"y":405}},"node:100015":{"location":{"x":5080,"y":405}},"node:100016":{"location":{"x":4160,"y":530}},"node:100017":{"location":{"x":4620,"y":530}},"node:100018":{"location":{"x":5080,"y":530}},"node:100019":{"location":{"x":4160,"y":655}},"node:100020":{"location":{"x":4620,"y":655}},"node:100021":{"location":{"x":5080,"y":655}},"node:100022":{"location":{"x":4160,"y":780}},"node:100023":{"location":{"x":4620,"y":780}},"node:100024":{"location":{"x":5080,"y":780}},"node:100025":{"location":{"x":4160,"y":905}},"node:100026":{"location":{"x":4620,"y":905}},"node:100027":{"location":{"x":5080,"y":905}},"node:100028":{"location":{"x":4160,"y":1030}},"node:100029":{"location":{"x":4620,"y":1030}},"node:100030":{"location":{"x":5080,"y":1030}},"node:100031":{"location":{"x":4160,"y":1155}},"node:100032":{"location":{"x":4620,"y":1155}},"node:100033":{"location":{"x":4160,"y":1280}},"node:100034":{"location":{"x":4620,"y":1280}},"node:100035":{"location":{"x":4160,"y":1405}},"node:100036":{"location":{"x":4160,"y":1530}},"node:100037":{"location":{"x":4160,"y":1655}},"node:100038":{"location":{"x":4620,"y":1655}},"node:100039":{"location":{"x":4160,"y":1780}},"node:100040":{"location":{"x":4160,"y":1905}},"node:100041":{"location":{"x":4620,"y":1905}},"node:100042":{"location":{"x":4160,"y":2030}},"node:100043":{"location":{"x":4620,"y":2030}},"node:100044":{"location":{"x":4160,"y":2155}},"node:100045":{"location":{"x":4620,"y":2155}},"node:100046":{"location":{"x":4160,"y":2280}},"node:100047":{"location":{"x":4620,"y":2280}},"node:100048":{"location":{"x":4160,"y":2405}},"node:100049":{"location":{"x":4620,"y":2405}},"node:100050":{"location":{"x":4160,"y":2530}},"node:100051":{"location":{"x":4620,"y":2530}},"node:100052":{"location":{"x":4160,"y":2655}},"node:100053":{"location":{"x":4620,"y":2655}},"node:100054":{"location":{"x":4160,"y":2780}},"node:100055":{"location":{"x":4620,"y":2780}},"node:100056":{"location":{"x":5080,"y":2780}},"node:100057":{"location":{"x":4160,"y":2905}},"node:100058":{"location":{"x":4620,"y":2905}},"node:100059":{"location":{"x":5080,"y":2905}},"node:100060":{"location":{"x":4160,"y":3030}},"node:100061":{"location":{"x":4620,"y":3030}},"node:100062":{"location":{"x":4160,"y":3155}},"node:100063":{"location":{"x":4620,"y":3155}},"node:100064":{"location":{"x":3700,"y":3280}},"node:100065":{"location":{"x":4160,"y":3280}},"node:100066":{"location":{"x":3700,"y":3405}},"node:100067":{"location":{"x":4160,"y":3405}},"node:100068":{"location":{"x":3700,"y":3530}},"node:100069":{"location":{"x":4160,"y":3530}},"node:100070":{"location":{"x":4620,"y":3530}},"node:100071":{"location":{"x":3700,"y":3655}},"node:100072":{"location":{"x":4160,"y":3655}},"node:100073":{"location":{"x":4620,"y":3655}},"node:100074":{"location":{"x":3700,"y":3780}},"node:100075":{"location":{"x":4160,"y":3780}},"node:100076":{"location":{"x":3700,"y":3905}},"node:100077":{"location":{"x":3700,"y":4030}},"node:100078":{"location":{"x":4160,"y":4030}},"node:100079":{"location":{"x":3700,"y":4155}},"node:100080":{"location":{"x":4160,"y":4155}},"node:100081":{"location":{"x":3700,"y":4280}},"node:100082":{"location":{"x":4160,"y":4280}},"node:100083":{"location":{"x":3700,"y":4405}},"node:100084":{"location":{"x":4160,"y":4405}},"node:100085":{"location":{"x":3700,"y":4530}},"node:100086":{"location":{"x":4160,"y":4530}},"node:100087":{"location":{"x":3700,"y":4655}},"node:100088":{"location":{"x":4160,"y":4655}},"node:100089":{"location":{"x":3700,"y":4780}},"node:100090":{"location":{"x":4160,"y":4780}},"node:100091":{"location":{"x":3240,"y":4905}},"node:100092":{"location":{"x":3700,"y":4905}},"node:100093":{"location":{"x":3240,"y":5030}},"node:100094":{"location":{"x":3700,"y":5030}},"node:100095":{"location":{"x":2780,"y":5155}},"node:100096":{"location":{"x":3240,"y":5155}},"node:100097":{"location":{"x":2780,"y":5280}},"node:100098":{"location":{"x":3240,"y":5280}},"node:100099":{"location":{"x":2780,"y":5405}},"node:100100":{"location":{"x":3240,"y":5405}},"node:100101":{"location":{"x":2780,"y":5530}},"node:100102":{"location":{"x":3240,"y":5530}},"node:100103":{"location":{"x":2780,"y":5655}},"node:100104":{"location":{"x":3240,"y":5655}},"node:100105":{"location":{"x":2780,"y":5780}},"node:100106":{"location":{"x":3240,"y":5780}},"node:100107":{"location":{"x":2780,"y":5905}},"node:100108":{"location":{"x":3240,"y":5905}},"node:100109":{"location":{"x":2320,"y":6030}},"node:100110":{"location":{"x":480,"y":6363}},"node:100111":{"location":{"x":940,"y":6363}},"node:100112":{"location":{"x":1400,"y":6363}},"node:100113":{"location":{"x":1860,"y":6363}},"node:100114":{"location":{"x":2320,"y":6155}},"node:100115":{"location":{"x":2780,"y":6155}},"node:100116":{"location":{"x":3240,"y":6155}},"node:100117":{"location":{"x":3700,"y":6155}},"node:100118":{"location":{"x":4160,"y":6155}},"node:100119":{"location":{"x":4620,"y":6155}},"node:100120":{"location":{"x":5080,"y":6155}},"node:100121":{"location":{"x":5540,"y":6155}},"node:100122":{"location":{"x":6000,"y":6155}},"node:100123":{"location":{"x":6460,"y":6155}},"node:100124":{"location":{"x":6920,"y":6155}},"node:100125":{"location":{"x":2320,"y":6342}},"node:100126":{"location":{"x":2780,"y":6280}},"node:100127":{"location":{"x":3240,"y":6280}},"node:100128":{"location":{"x":3700,"y":6280}},"node:100129":{"location":{"x":2780,"y":6405}},"node:100130":{"location":{"x":3240,"y":6405}},"node:100131":{"location":{"x":2320,"y":6592}},"node:100132":{"location":{"x":2780,"y":6530}},"node:100133":{"location":{"x":3240,"y":6530}},"node:100134":{"location":{"x":3700,"y":6530}},"node:100135":{"location":{"x":2780,"y":6655}},"node:100136":{"location":{"x":3240,"y":6655}},"node:100137":{"location":{"x":480,"y":6842}},"node:100138":{"location":{"x":940,"y":6842}},"node:100139":{"location":{"x":1400,"y":6780}},"node:100140":{"location":{"x":1400,"y":6905}},"node:100141":{"location":{"x":1860,"y":6905}},"node:100142":{"location":{"x":480,"y":7092}},"node:100143":{"location":{"x":940,"y":7092}},"node:100144":{"location":{"x":1400,"y":7030}},"node:100145":{"location":{"x":1400,"y":7155}},"node:200000":{"location":{"x":250,"y":6128}},"node:200001":{"location":{"x":710,"y":5736}},"node:200002":{"location":{"x":1170,"y":5736}},"node:200003":{"location":{"x":1630,"y":5736}},"node:200004":{"location":{"x":2090,"y":5582}},"node:200005":{"location":{"x":2550,"y":5020}},"node:200006":{"location":{"x":3010,"y":4241}},"node:200007":{"location":{"x":3470,"y":2739}},"node:200008":{"location":{"x":3930,"y":826}},"node:200009":{"location":{"x":3930,"y":888}},"node:200010":{"location":{"x":3930,"y":951}},"node:200011":{"location":{"x":4390,"y":295}},"node:200012":{"location":{"x":3930,"y":1013}},"node:200013":{"location":{"x":4390,"y":420}},"node:200014":{"location":{"x":4850,"y":420}},"node:200015":{"location":{"x":3930,"y":1076}},"node:200016":{"location":{"x":4390,"y":545}},"node:200017":{"location":{"x":4850,"y":545}},"node:200018":{"location":{"x":3930,"y":1138}},"node:200019":{"location":{"x":4390,"y":670}},"node:200020":{"location":{"x":4850,"y":670}},"node:200021":{"location":{"x":3930,"y":1201}},"node:200022":{"location":{"x":4390,"y":795}},"node:200023":{"location":{"x":4850,"y":795}},"node:200024":{"location":{"x":3930,"y":1263}},"node:200025":{"location":{"x":4390,"y":920}},"node:200026":{"location":{"x":4850,"y":920}},"node:200027":{"location":{"x":3930,"y":1326}},"node:200028":{"location":{"x":4390,"y":1045}},"node:200029":{"location":{"x":4850,"y":1045}},"node:200030":{"location":{"x":3930,"y":1388}},"node:200031":{"location":{"x":4390,"y":1170}},"node:200032":{"location":{"x":3930,"y":1451}},"node:200033":{"location":{"x":4390,"y":1295}},"node:200034":{"location":{"x":3930,"y":1513}},"node:200035":{"location":{"x":3930,"y":1576}},"node:200036":{"location":{"x":3930,"y":1638}},"node:200037":{"location":{"x":4390,"y":1670}},"node:200038":{"location":{"x":3930,"y":1701}},"node:200039":{"location":{"x":3930,"y":1763}},"node:200040":{"location":{"x":4390,"y":1920}},"node:200041":{"location":{"x":3930,"y":1826}},"node:200042":{"location":{"x":4390,"y":2045}},"node:200043":{"location":{"x":3930,"y":1888}},"node:200044":{"location":{"x":4390,"y":2170}},"node:200045":{"location":{"x":3930,"y":1951}},"node:200046":{"location":{"x":4390,"y":2295}},"node:200047":{"location":{"x":3930,"y":2013}},"node:200048":{"location":{"x":4390,"y":2420}},"node:200049":{"location":{"x":3930,"y":2076}},"node:200050":{"location":{"x":4390,"y":2545}},"node:200051":{"location":{"x":3930,"y":2138}},"node:200052":{"location":{"x":4390,"y":2670}},"node:200053":{"location":{"x":3930,"y":2201}},"node:200054":{"location":{"x":4390,"y":2795}},"node:200055":{"location":{"x":4850,"y":2795}},"node:200056":{"location":{"x":3930,"y":2263}},"node:200057":{"location":{"x":4390,"y":2920}},"node:200058":{"location":{"x":4850,"y":2920}},"node:200059":{"location":{"x":3930,"y":2326}},"node:200060":{"location":{"x":4390,"y":3045}},"node:200061":{"location":{"x":3930,"y":2388}},"node:200062":{"location":{"x":4390,"y":3170}},"node:200063":{"location":{"x":3470,"y":3582}},"node:200064":{"location":{"x":3930,"y":3295}},"node:200065":{"location":{"x":3470,"y":3645}},"node:200066":{"location":{"x":3930,"y":3420}},"node:200067":{"location":{"x":3470,"y":3707}},"node:200068":{"location":{"x":3930,"y":3545}},"node:200069":{"location":{"x":4390,"y":3545}},"node:200070":{"location":{"x":3470,"y":3770}},"node:200071":{"location":{"x":3930,"y":3670}},"node:200072":{"location":{"x":4390,"y":3670}},"node:200073":{"location":{"x":3470,"y":3832}},"node:200074":{"location":{"x":3930,"y":3795}},"node:200075":{"location":{"x":3470,"y":3895}},"node:200076":{"location":{"x":3470,"y":3957}},"node:200077":{"location":{"x":3930,"y":4045}},"node:200078":{"location":{"x":3470,"y":4020}},"node:200079":{"location":{"x":3930,"y":4170}},"node:200080":{"location":{"x":3470,"y":4082}},"node:200081":{"location":{"x":3930,"y":4295}},"node:200082":{"location":{"x":3470,"y":4145}},"node:200083":{"location":{"x":3930,"y":4420}},"node:200084":{"location":{"x":3470,"y":4207}},"node:200085":{"location":{"x":3930,"y":4545}},"node:200086":{"location":{"x":3470,"y":4270}},"node:200087":{"location":{"x":3930,"y":4670}},"node:200088":{"location":{"x":3470,"y":4332}},"node:200089":{"location":{"x":3930,"y":4795}},"node:200090":{"location":{"x":3010,"y":4765}},"node:200091":{"location":{"x":3470,"y":4920}},"node:200092":{"location":{"x":3010,"y":4828}},"node:200093":{"location":{"x":3470,"y":5045}},"node:200094":{"location":{"x":2550,"y":5299}},"node:200095":{"location":{"x":3010,"y":5170}},"node:200096":{"location":{"x":2550,"y":5361}},"node:200097":{"location":{"x":3010,"y":5295}},"node:200098":{"location":{"x":2550,"y":5424}},"node:200099":{"location":{"x":3010,"y":5420}},"node:200100":{"location":{"x":2550,"y":5486}},"node:200101":{"location":{"x":3010,"y":5545}},"node:200102":{"location":{"x":2550,"y":5549}},"node:200103":{"location":{"x":3010,"y":5670}},"node:200104":{"location":{"x":2550,"y":5611}},"node:200105":{"location":{"x":3010,"y":5795}},"node:200106":{"location":{"x":2550,"y":5674}},"node:200107":{"location":{"x":3010,"y":5920}},"node:200108":{"location":{"x":2090,"y":5890}},"node:200109":{"location":{"x":250,"y":6449}},"node:200110":{"location":{"x":710,"y":6378}},"node:200111":{"location":{"x":1170,"y":6378}},"node:200112":{"location":{"x":1630,"y":6378}},"node:200113":{"location":{"x":2090,"y":6274}},"node:200114":{"location":{"x":2550,"y":6170}},"node:200115":{"location":{"x":3010,"y":6170}},"node:200116":{"location":{"x":3470,"y":6170}},"node:200117":{"location":{"x":3930,"y":6170}},"node:200118":{"location":{"x":4390,"y":6170}},"node:200119":{"location":{"x":4850,"y":6170}},"node:200120":{"location":{"x":5310,"y":6170}},"node:200121":{"location":{"x":5770,"y":6170}},"node:200122":{"location":{"x":6230,"y":6170}},"node:200123":{"location":{"x":6690,"y":6170}},"node:200124":{"location":{"x":2090,"y":6367}},"node:200125":{"location":{"x":2550,"y":6326}},"node:200126":{"location":{"x":3010,"y":6295}},"node:200127":{"location":{"x":3470,"y":6295}},"node:200128":{"location":{"x":2550,"y":6388}},"node:200129":{"location":{"x":3010,"y":6420}},"node:200130":{"location":{"x":2090,"y":6492}},"node:200131":{"location":{"x":2550,"y":6576}},"node:200132":{"location":{"x":3010,"y":6545}},"node:200133":{"location":{"x":3470,"y":6545}},"node:200134":{"location":{"x":2550,"y":6638}},"node:200135":{"location":{"x":3010,"y":6670}},"node:200136":{"location":{"x":250,"y":6688}},"node:200137":{"location":{"x":710,"y":6857}},"node:200138":{"location":{"x":1170,"y":6826}},"node:200139":{"location":{"x":1170,"y":6888}},"node:200140":{"location":{"x":1630,"y":6920}},"node:200141":{"location":{"x":250,"y":6813}},"node:200142":{"location":{"x":710,"y":7107}},"node:200143":{"location":{"x":1170,"y":7076}},"node:200144":{"location":{"x":1170,"y":7138}}},"selection":null,"view":{"scroll":{"x":-0,"y":0},"visible_rect":{"max":{"x":404,"y":438},"min":{"x":-0,"y":0}},"zoom":1}}